infi.clickhouse_orm-2.1.1-py3.8-nspkg.pth
infi/clickhouse_orm/__init__.py
infi/clickhouse_orm/__version__.py
infi/clickhouse_orm/database.py
infi/clickhouse_orm/engines.py
infi/clickhouse_orm/fields.py
infi/clickhouse_orm/funcs.py
infi/clickhouse_orm/migrations.py
infi/clickhouse_orm/models.py
infi/clickhouse_orm/query.py
infi/clickhouse_orm/system_models.py
infi/clickhouse_orm/utils.py
infi.clickhouse_orm-2.1.1.dist-info/LICENSE
infi.clickhouse_orm-2.1.1.dist-info/METADATA
infi.clickhouse_orm-2.1.1.dist-info/WHEEL
infi.clickhouse_orm-2.1.1.dist-info/entry_points.txt
infi.clickhouse_orm-2.1.1.dist-info/namespace_packages.txt
infi.clickhouse_orm-2.1.1.dist-info/top_level.txt
infi.clickhouse_orm-2.1.1.dist-info/RECORD
