Metadata-Version: 2.1
Name: infi.clickhouse-orm
Version: 2.1.1
Summary: A Python library for working with the ClickHouse database
Home-page: https://github.com/Infinidat/infi.clickhouse_orm
Author: Jenkins CI
Author-email: noreply@infinidat.com
License: BSD
Platform: UNKNOWN
Classifier: Intended Audience :: Developers
Classifier: Intended Audience :: System Administrators
Classifier: License :: OSI Approved :: BSD License
Classifier: Operating System :: OS Independent
Classifier: Programming Language :: Python
Classifier: Programming Language :: Python :: 2.7
Classifier: Programming Language :: Python :: 3.4
Classifier: Topic :: Software Development :: Libraries :: Python Modules
Classifier: Topic :: Database
Requires-Dist: iso8601 (>=0.1.12)
Requires-Dist: pytz
Requires-Dist: requests
Requires-Dist: setuptools
